pybarcodes/__init__.py
pybarcodes/barcode.py
pybarcodes/codes.py
pybarcodes/codings/__init__.py
pybarcodes/codings/codex.py
pybarcodes/codings/ean.py
pybarcodes/ean.py
pybarcodes/exceptions.py
pybarcodes/fonts/arial.ttf
pybarcodes-1.0.1.dist-info/LICENSE
pybarcodes-1.0.1.dist-info/METADATA
pybarcodes-1.0.1.dist-info/WHEEL
pybarcodes-1.0.1.dist-info/RECORD
