Metadata-Version: 2.3
Name: pybarcodes
Version: 1.0.1
Summary: A Python package for barcode generation
License: MIT
Keywords: barcode,scanner,generator,ean13,code39,jan,python
Author: atbuy
Author-email: buy@atbuy.dev
Requires-Python: >=3.9,<4.0
Classifier: Development Status :: 5 - Production/Stable
Classifier: Intended Audience :: Developers
Classifier: License :: OSI Approved :: MIT License
Classifier: Natural Language :: English
Classifier: Operating System :: OS Independent
Classifier: Programming Language :: Python
Classifier: Programming Language :: Python :: 3
Classifier: Programming Language :: Python :: 3.9
Classifier: Programming Language :: Python :: 3.10
Classifier: Programming Language :: Python :: 3.11
Classifier: Programming Language :: Python :: 3.12
Classifier: Programming Language :: Python :: 3.13
Classifier: Topic :: Multimedia :: Graphics
Classifier: Topic :: Software Development :: Libraries
Classifier: Topic :: Software Development :: Libraries :: Python Modules
Classifier: Topic :: Utilities
Requires-Dist: pillow (>8,<12)
Project-URL: Bug Tracker, https://github.com/atbuy/pybarcodes/issues
Project-URL: CI/CD, https://github.com/atbuy/pybarcodes/actions
Project-URL: Homepage, https://github.com/atbuy/pybarcodes
Project-URL: Repository, https://github.com/atbuy/pybarcodes
Project-URL: Source Code, https://github.com/atbuy/pybarcodes
